aditi301026/__init__.py
aditi301026/main_code.py
aditi301026-0.1.2.dist-info/licenses/LICENSE
aditi301026-0.1.2.dist-info/METADATA
aditi301026-0.1.2.dist-info/WHEEL
aditi301026-0.1.2.dist-info/top_level.txt
aditi301026-0.1.2.dist-info/RECORD
