Metadata-Version: 2.4
Name: aditi301026
Version: 0.1.2
Summary: This module contains two codes Frist one to calculate attendance and second to calculate result for students
Author-email: Aditi Jain <aditi.jain3010@email.com>
Classifier: Programming Language :: Python :: 3
Classifier: License :: OSI Approved :: MIT License
Classifier: Operating System :: OS Independent
Requires-Python: >=3.8
License-File: LICENSE
Dynamic: license-file
